{
  "title": "İstanbul Ankara Evden Eve Nakliyat",
  "description": "İstanbul’dan Ankara’ya güvenli nakliye: çift kat paketleme, fotoğraflı envanter, tek ekip lideri, şeffaf evden eve nakliyat ücreti.\n",
  "keywords": [
    "istanbul ankara nakliyat",
    "evden eve nakliyat",
    "istanbul ankara taşımacılık",
    "nakliyat firması",
    "sigortalı nakliyat",
    "profesyonel nakliyat"
  ],
  "author": "KARAKAR Web",
  "robots": "index, follow",
  "canonical": "https://istanbulankaraevdenevenakliye.com.tr",
  "language": "tr"
}